{
  "name": "Super Admin",
  "code": "strapi-super-admin",
  "description": "Super Admins can access and manage all features and settings.",
  "permissions": [
    {
      "action": "plugin::content-manager.explorer.create",
      "subject": "api::artist.artist",
      "properties": {
        "fields": [
          "name",
          "picture",
          "description",
          "contributions",
          "tracks",
          "releases",
          "presence",
          "bio",
          "website"
        ],
        "locales": [
          "en",
          "fr"
        ]
      },
      "conditions": []
    },
    {
      "action": "plugin::content-manager.explorer.delete",
      "subject": "api::artist.artist",
      "properties": {
        "locales": [
          "en",
          "fr"
        ]
      },
      "conditions": []
    },
    {
      "action": "plugin::content-manager.explorer.publish",
      "subject": "api::artist.artist",
      "properties": {
        "locales": [
          "en",
          "fr"
        ]
      },
      "conditions": []
    },
    {
      "action": "plugin::content-manager.explorer.read",
      "subject": "api::artist.artist",
      "properties": {
        "fields": [
          "name",
          "picture",
          "description",
          "contributions",
          "tracks",
          "releases",
          "presence",
          "bio",
          "website"
        ],
        "locales": [
          "en",
          "fr"
        ]
      },
      "conditions": []
    },
    {
      "action": "plugin::content-manager.explorer.update",
      "subject": "api::artist.artist",
      "properties": {
        "fields": [
          "name",
          "picture",
          "description",
          "contributions",
          "tracks",
          "releases",
          "presence",
          "bio",
          "website"
        ],
        "locales": [
          "en",
          "fr"
        ]
      },
      "conditions": []
    },
    {
      "action": "plugin::content-manager.explorer.create",
      "subject": "api::bio.bio",
      "properties": {
        "fields": [
          "title",
          "blocks",
          "seo.metaTitle",
          "seo.metaDescription",
          "seo.metaImage",
          "seo.metaSocial.socialNetwork",
          "seo.metaSocial.title",
          "seo.metaSocial.description",
          "seo.metaSocial.image",
          "seo.keywords",
          "seo.metaRobots",
          "seo.structuredData",
          "seo.metaViewport",
          "seo.canonicalURL",
          "seo.noIndex",
          "artist"
        ],
        "locales": [
          "en",
          "fr"
        ]
      },
      "conditions": []
    },
    {
      "action": "plugin::content-manager.explorer.delete",
      "subject": "api::bio.bio",
      "properties": {
        "locales": [
          "en",
          "fr"
        ]
      },
      "conditions": []
    },
    {
      "action": "plugin::content-manager.explorer.publish",
      "subject": "api::bio.bio",
      "properties": {
        "locales": [
          "en",
          "fr"
        ]
      },
      "conditions": []
    },
    {
      "action": "plugin::content-manager.explorer.read",
      "subject": "api::bio.bio",
      "properties": {
        "fields": [
          "title",
          "blocks",
          "seo.metaTitle",
          "seo.metaDescription",
          "seo.metaImage",
          "seo.metaSocial.socialNetwork",
          "seo.metaSocial.title",
          "seo.metaSocial.description",
          "seo.metaSocial.image",
          "seo.keywords",
          "seo.metaRobots",
          "seo.structuredData",
          "seo.metaViewport",
          "seo.canonicalURL",
          "seo.noIndex",
          "artist"
        ],
        "locales": [
          "en",
          "fr"
        ]
      },
      "conditions": []
    },
    {
      "action": "plugin::content-manager.explorer.update",
      "subject": "api::bio.bio",
      "properties": {
        "fields": [
          "title",
          "blocks",
          "seo.metaTitle",
          "seo.metaDescription",
          "seo.metaImage",
          "seo.metaSocial.socialNetwork",
          "seo.metaSocial.title",
          "seo.metaSocial.description",
          "seo.metaSocial.image",
          "seo.keywords",
          "seo.metaRobots",
          "seo.structuredData",
          "seo.metaViewport",
          "seo.canonicalURL",
          "seo.noIndex",
          "artist"
        ],
        "locales": [
          "en",
          "fr"
        ]
      },
      "conditions": []
    },
    {
      "action": "plugin::content-manager.explorer.create",
      "subject": "api::genre.genre",
      "properties": {
        "fields": [
          "name",
          "tracks"
        ]
      },
      "conditions": []
    },
    {
      "action": "plugin::content-manager.explorer.delete",
      "subject": "api::genre.genre",
      "properties": {},
      "conditions": []
    },
    {
      "action": "plugin::content-manager.explorer.publish",
      "subject": "api::genre.genre",
      "properties": {},
      "conditions": []
    },
    {
      "action": "plugin::content-manager.explorer.read",
      "subject": "api::genre.genre",
      "properties": {
        "fields": [
          "name",
          "tracks"
        ]
      },
      "conditions": []
    },
    {
      "action": "plugin::content-manager.explorer.update",
      "subject": "api::genre.genre",
      "properties": {
        "fields": [
          "name",
          "tracks"
        ]
      },
      "conditions": []
    },
    {
      "action": "plugin::content-manager.explorer.create",
      "subject": "api::label.label",
      "properties": {
        "fields": [
          "name",
          "releases"
        ],
        "locales": [
          "en",
          "fr"
        ]
      },
      "conditions": []
    },
    {
      "action": "plugin::content-manager.explorer.delete",
      "subject": "api::label.label",
      "properties": {
        "locales": [
          "en",
          "fr"
        ]
      },
      "conditions": []
    },
    {
      "action": "plugin::content-manager.explorer.publish",
      "subject": "api::label.label",
      "properties": {
        "locales": [
          "en",
          "fr"
        ]
      },
      "conditions": []
    },
    {
      "action": "plugin::content-manager.explorer.read",
      "subject": "api::label.label",
      "properties": {
        "fields": [
          "name",
          "releases"
        ],
        "locales": [
          "en",
          "fr"
        ]
      },
      "conditions": []
    },
    {
      "action": "plugin::content-manager.explorer.update",
      "subject": "api::label.label",
      "properties": {
        "fields": [
          "name",
          "releases"
        ],
        "locales": [
          "en",
          "fr"
        ]
      },
      "conditions": []
    },
    {
      "action": "plugin::content-manager.explorer.create",
      "subject": "api::locale-type.locale-type",
      "properties": {
        "fields": [
          "shortCode",
          "fullCode",
          "label",
          "localizedLabel"
        ],
        "locales": [
          "en",
          "fr"
        ]
      },
      "conditions": []
    },
    {
      "action": "plugin::content-manager.explorer.delete",
      "subject": "api::locale-type.locale-type",
      "properties": {
        "locales": [
          "en",
          "fr"
        ]
      },
      "conditions": []
    },
    {
      "action": "plugin::content-manager.explorer.read",
      "subject": "api::locale-type.locale-type",
      "properties": {
        "fields": [
          "shortCode",
          "fullCode",
          "label",
          "localizedLabel"
        ],
        "locales": [
          "en",
          "fr"
        ]
      },
      "conditions": []
    },
    {
      "action": "plugin::content-manager.explorer.update",
      "subject": "api::locale-type.locale-type",
      "properties": {
        "fields": [
          "shortCode",
          "fullCode",
          "label",
          "localizedLabel"
        ],
        "locales": [
          "en",
          "fr"
        ]
      },
      "conditions": []
    },
    {
      "action": "plugin::content-manager.explorer.create",
      "subject": "api::page-home.page-home",
      "properties": {
        "fields": [
          "title",
          "blocks",
          "seo.metaTitle",
          "seo.metaDescription",
          "seo.metaImage",
          "seo.metaSocial.socialNetwork",
          "seo.metaSocial.title",
          "seo.metaSocial.description",
          "seo.metaSocial.image",
          "seo.keywords",
          "seo.metaRobots",
          "seo.structuredData",
          "seo.metaViewport",
          "seo.canonicalURL",
          "seo.noIndex"
        ],
        "locales": [
          "en",
          "fr"
        ]
      },
      "conditions": []
    },
    {
      "action": "plugin::content-manager.explorer.delete",
      "subject": "api::page-home.page-home",
      "properties": {
        "locales": [
          "en",
          "fr"
        ]
      },
      "conditions": []
    },
    {
      "action": "plugin::content-manager.explorer.publish",
      "subject": "api::page-home.page-home",
      "properties": {
        "locales": [
          "en",
          "fr"
        ]
      },
      "conditions": []
    },
    {
      "action": "plugin::content-manager.explorer.read",
      "subject": "api::page-home.page-home",
      "properties": {
        "fields": [
          "title",
          "blocks",
          "seo.metaTitle",
          "seo.metaDescription",
          "seo.metaImage",
          "seo.metaSocial.socialNetwork",
          "seo.metaSocial.title",
          "seo.metaSocial.description",
          "seo.metaSocial.image",
          "seo.keywords",
          "seo.metaRobots",
          "seo.structuredData",
          "seo.metaViewport",
          "seo.canonicalURL",
          "seo.noIndex"
        ],
        "locales": [
          "en",
          "fr"
        ]
      },
      "conditions": []
    },
    {
      "action": "plugin::content-manager.explorer.update",
      "subject": "api::page-home.page-home",
      "properties": {
        "fields": [
          "title",
          "blocks",
          "seo.metaTitle",
          "seo.metaDescription",
          "seo.metaImage",
          "seo.metaSocial.socialNetwork",
          "seo.metaSocial.title",
          "seo.metaSocial.description",
          "seo.metaSocial.image",
          "seo.keywords",
          "seo.metaRobots",
          "seo.structuredData",
          "seo.metaViewport",
          "seo.canonicalURL",
          "seo.noIndex"
        ],
        "locales": [
          "en",
          "fr"
        ]
      },
      "conditions": []
    },
    {
      "action": "plugin::content-manager.explorer.create",
      "subject": "api::page404.page404",
      "properties": {
        "fields": [
          "title",
          "message",
          "seo.metaTitle",
          "seo.metaDescription",
          "seo.metaImage",
          "seo.metaSocial.socialNetwork",
          "seo.metaSocial.title",
          "seo.metaSocial.description",
          "seo.metaSocial.image",
          "seo.keywords",
          "seo.metaRobots",
          "seo.structuredData",
          "seo.metaViewport",
          "seo.canonicalURL",
          "seo.noIndex"
        ],
        "locales": [
          "en",
          "fr"
        ]
      },
      "conditions": []
    },
    {
      "action": "plugin::content-manager.explorer.delete",
      "subject": "api::page404.page404",
      "properties": {
        "locales": [
          "en",
          "fr"
        ]
      },
      "conditions": []
    },
    {
      "action": "plugin::content-manager.explorer.publish",
      "subject": "api::page404.page404",
      "properties": {
        "locales": [
          "en",
          "fr"
        ]
      },
      "conditions": []
    },
    {
      "action": "plugin::content-manager.explorer.read",
      "subject": "api::page404.page404",
      "properties": {
        "fields": [
          "title",
          "message",
          "seo.metaTitle",
          "seo.metaDescription",
          "seo.metaImage",
          "seo.metaSocial.socialNetwork",
          "seo.metaSocial.title",
          "seo.metaSocial.description",
          "seo.metaSocial.image",
          "seo.keywords",
          "seo.metaRobots",
          "seo.structuredData",
          "seo.metaViewport",
          "seo.canonicalURL",
          "seo.noIndex"
        ],
        "locales": [
          "en",
          "fr"
        ]
      },
      "conditions": []
    },
    {
      "action": "plugin::content-manager.explorer.update",
      "subject": "api::page404.page404",
      "properties": {
        "fields": [
          "title",
          "message",
          "seo.metaTitle",
          "seo.metaDescription",
          "seo.metaImage",
          "seo.metaSocial.socialNetwork",
          "seo.metaSocial.title",
          "seo.metaSocial.description",
          "seo.metaSocial.image",
          "seo.keywords",
          "seo.metaRobots",
          "seo.structuredData",
          "seo.metaViewport",
          "seo.canonicalURL",
          "seo.noIndex"
        ],
        "locales": [
          "en",
          "fr"
        ]
      },
      "conditions": []
    },
    {
      "action": "plugin::content-manager.explorer.create",
      "subject": "api::page500.page500",
      "properties": {
        "fields": [
          "title",
          "message",
          "seo.metaTitle",
          "seo.metaDescription",
          "seo.metaImage",
          "seo.metaSocial.socialNetwork",
          "seo.metaSocial.title",
          "seo.metaSocial.description",
          "seo.metaSocial.image",
          "seo.keywords",
          "seo.metaRobots",
          "seo.structuredData",
          "seo.metaViewport",
          "seo.canonicalURL",
          "seo.noIndex"
        ],
        "locales": [
          "en",
          "fr"
        ]
      },
      "conditions": []
    },
    {
      "action": "plugin::content-manager.explorer.delete",
      "subject": "api::page500.page500",
      "properties": {
        "locales": [
          "en",
          "fr"
        ]
      },
      "conditions": []
    },
    {
      "action": "plugin::content-manager.explorer.publish",
      "subject": "api::page500.page500",
      "properties": {
        "locales": [
          "en",
          "fr"
        ]
      },
      "conditions": []
    },
    {
      "action": "plugin::content-manager.explorer.read",
      "subject": "api::page500.page500",
      "properties": {
        "fields": [
          "title",
          "message",
          "seo.metaTitle",
          "seo.metaDescription",
          "seo.metaImage",
          "seo.metaSocial.socialNetwork",
          "seo.metaSocial.title",
          "seo.metaSocial.description",
          "seo.metaSocial.image",
          "seo.keywords",
          "seo.metaRobots",
          "seo.structuredData",
          "seo.metaViewport",
          "seo.canonicalURL",
          "seo.noIndex"
        ],
        "locales": [
          "en",
          "fr"
        ]
      },
      "conditions": []
    },
    {
      "action": "plugin::content-manager.explorer.update",
      "subject": "api::page500.page500",
      "properties": {
        "fields": [
          "title",
          "message",
          "seo.metaTitle",
          "seo.metaDescription",
          "seo.metaImage",
          "seo.metaSocial.socialNetwork",
          "seo.metaSocial.title",
          "seo.metaSocial.description",
          "seo.metaSocial.image",
          "seo.keywords",
          "seo.metaRobots",
          "seo.structuredData",
          "seo.metaViewport",
          "seo.canonicalURL",
          "seo.noIndex"
        ],
        "locales": [
          "en",
          "fr"
        ]
      },
      "conditions": []
    },
    {
      "action": "plugin::content-manager.explorer.create",
      "subject": "api::project.project",
      "properties": {
        "fields": [
          "name",
          "public",
          "seo.metaTitle",
          "seo.metaDescription",
          "seo.metaImage",
          "seo.metaSocial.socialNetwork",
          "seo.metaSocial.title",
          "seo.metaSocial.description",
          "seo.metaSocial.image",
          "seo.keywords",
          "seo.metaRobots",
          "seo.structuredData",
          "seo.metaViewport",
          "seo.canonicalURL",
          "seo.noIndex",
          "blocks",
          "password",
          "slug"
        ],
        "locales": [
          "en",
          "fr"
        ]
      },
      "conditions": []
    },
    {
      "action": "plugin::content-manager.explorer.delete",
      "subject": "api::project.project",
      "properties": {
        "locales": [
          "en",
          "fr"
        ]
      },
      "conditions": []
    },
    {
      "action": "plugin::content-manager.explorer.publish",
      "subject": "api::project.project",
      "properties": {
        "locales": [
          "en",
          "fr"
        ]
      },
      "conditions": []
    },
    {
      "action": "plugin::content-manager.explorer.read",
      "subject": "api::project.project",
      "properties": {
        "fields": [
          "name",
          "public",
          "seo.metaTitle",
          "seo.metaDescription",
          "seo.metaImage",
          "seo.metaSocial.socialNetwork",
          "seo.metaSocial.title",
          "seo.metaSocial.description",
          "seo.metaSocial.image",
          "seo.keywords",
          "seo.metaRobots",
          "seo.structuredData",
          "seo.metaViewport",
          "seo.canonicalURL",
          "seo.noIndex",
          "blocks",
          "password",
          "slug"
        ],
        "locales": [
          "en",
          "fr"
        ]
      },
      "conditions": []
    },
    {
      "action": "plugin::content-manager.explorer.update",
      "subject": "api::project.project",
      "properties": {
        "fields": [
          "name",
          "public",
          "seo.metaTitle",
          "seo.metaDescription",
          "seo.metaImage",
          "seo.metaSocial.socialNetwork",
          "seo.metaSocial.title",
          "seo.metaSocial.description",
          "seo.metaSocial.image",
          "seo.keywords",
          "seo.metaRobots",
          "seo.structuredData",
          "seo.metaViewport",
          "seo.canonicalURL",
          "seo.noIndex",
          "blocks",
          "password",
          "slug"
        ],
        "locales": [
          "en",
          "fr"
        ]
      },
      "conditions": []
    },
    {
      "action": "plugin::content-manager.explorer.create",
      "subject": "api::record-type.record-type",
      "properties": {
        "fields": [
          "name"
        ],
        "locales": [
          "en",
          "fr"
        ]
      },
      "conditions": []
    },
    {
      "action": "plugin::content-manager.explorer.delete",
      "subject": "api::record-type.record-type",
      "properties": {
        "locales": [
          "en",
          "fr"
        ]
      },
      "conditions": []
    },
    {
      "action": "plugin::content-manager.explorer.read",
      "subject": "api::record-type.record-type",
      "properties": {
        "fields": [
          "name"
        ],
        "locales": [
          "en",
          "fr"
        ]
      },
      "conditions": []
    },
    {
      "action": "plugin::content-manager.explorer.update",
      "subject": "api::record-type.record-type",
      "properties": {
        "fields": [
          "name"
        ],
        "locales": [
          "en",
          "fr"
        ]
      },
      "conditions": []
    },
    {
      "action": "plugin::content-manager.explorer.create",
      "subject": "api::release.release",
      "properties": {
        "fields": [
          "title",
          "releaseDate",
          "cover",
          "tracks",
          "recordType",
          "artist",
          "contributors",
          "label"
        ]
      },
      "conditions": []
    },
    {
      "action": "plugin::content-manager.explorer.delete",
      "subject": "api::release.release",
      "properties": {},
      "conditions": []
    },
    {
      "action": "plugin::content-manager.explorer.publish",
      "subject": "api::release.release",
      "properties": {},
      "conditions": []
    },
    {
      "action": "plugin::content-manager.explorer.read",
      "subject": "api::release.release",
      "properties": {
        "fields": [
          "title",
          "releaseDate",
          "cover",
          "tracks",
          "recordType",
          "artist",
          "contributors",
          "label"
        ]
      },
      "conditions": []
    },
    {
      "action": "plugin::content-manager.explorer.update",
      "subject": "api::release.release",
      "properties": {
        "fields": [
          "title",
          "releaseDate",
          "cover",
          "tracks",
          "recordType",
          "artist",
          "contributors",
          "label"
        ]
      },
      "conditions": []
    },
    {
      "action": "plugin::content-manager.explorer.create",
      "subject": "api::track.track",
      "properties": {
        "fields": [
          "title",
          "releaseDate",
          "bpm",
          "duration",
          "releasePosition",
          "contributors",
          "artist",
          "genres",
          "release",
          "file"
        ]
      },
      "conditions": []
    },
    {
      "action": "plugin::content-manager.explorer.delete",
      "subject": "api::track.track",
      "properties": {},
      "conditions": []
    },
    {
      "action": "plugin::content-manager.explorer.publish",
      "subject": "api::track.track",
      "properties": {},
      "conditions": []
    },
    {
      "action": "plugin::content-manager.explorer.read",
      "subject": "api::track.track",
      "properties": {
        "fields": [
          "title",
          "releaseDate",
          "bpm",
          "duration",
          "releasePosition",
          "contributors",
          "artist",
          "genres",
          "release",
          "file"
        ]
      },
      "conditions": []
    },
    {
      "action": "plugin::content-manager.explorer.update",
      "subject": "api::track.track",
      "properties": {
        "fields": [
          "title",
          "releaseDate",
          "bpm",
          "duration",
          "releasePosition",
          "contributors",
          "artist",
          "genres",
          "release",
          "file"
        ]
      },
      "conditions": []
    },
    {
      "action": "plugin::content-manager.explorer.create",
      "subject": "api::website.website",
      "properties": {
        "fields": [
          "adminUsers",
          "name",
          "favicon",
          "locales",
          "defaultLocale",
          "domain",
          "seo.metaTitle",
          "seo.metaDescription",
          "seo.metaImage",
          "seo.metaSocial.socialNetwork",
          "seo.metaSocial.title",
          "seo.metaSocial.description",
          "seo.metaSocial.image",
          "seo.keywords",
          "seo.metaRobots",
          "seo.structuredData",
          "seo.metaViewport",
          "seo.canonicalURL",
          "seo.noIndex",
          "type",
          "artist"
        ],
        "locales": [
          "en",
          "fr"
        ]
      },
      "conditions": []
    },
    {
      "action": "plugin::content-manager.explorer.delete",
      "subject": "api::website.website",
      "properties": {
        "locales": [
          "en",
          "fr"
        ]
      },
      "conditions": []
    },
    {
      "action": "plugin::content-manager.explorer.read",
      "subject": "api::website.website",
      "properties": {
        "fields": [
          "adminUsers",
          "name",
          "favicon",
          "locales",
          "defaultLocale",
          "domain",
          "seo.metaTitle",
          "seo.metaDescription",
          "seo.metaImage",
          "seo.metaSocial.socialNetwork",
          "seo.metaSocial.title",
          "seo.metaSocial.description",
          "seo.metaSocial.image",
          "seo.keywords",
          "seo.metaRobots",
          "seo.structuredData",
          "seo.metaViewport",
          "seo.canonicalURL",
          "seo.noIndex",
          "type",
          "artist"
        ],
        "locales": [
          "en",
          "fr"
        ]
      },
      "conditions": []
    },
    {
      "action": "plugin::content-manager.explorer.update",
      "subject": "api::website.website",
      "properties": {
        "fields": [
          "adminUsers",
          "name",
          "favicon",
          "locales",
          "defaultLocale",
          "domain",
          "seo.metaTitle",
          "seo.metaDescription",
          "seo.metaImage",
          "seo.metaSocial.socialNetwork",
          "seo.metaSocial.title",
          "seo.metaSocial.description",
          "seo.metaSocial.image",
          "seo.keywords",
          "seo.metaRobots",
          "seo.structuredData",
          "seo.metaViewport",
          "seo.canonicalURL",
          "seo.noIndex",
          "type",
          "artist"
        ],
        "locales": [
          "en",
          "fr"
        ]
      },
      "conditions": []
    },
    {
      "action": "admin::api-tokens.create",
      "subject": null,
      "properties": {},
      "conditions": []
    },
    {
      "action": "admin::api-tokens.delete",
      "subject": null,
      "properties": {},
      "conditions": []
    },
    {
      "action": "admin::api-tokens.read",
      "subject": null,
      "properties": {},
      "conditions": []
    },
    {
      "action": "admin::api-tokens.update",
      "subject": null,
      "properties": {},
      "conditions": []
    },
    {
      "action": "admin::marketplace.plugins.install",
      "subject": null,
      "properties": {},
      "conditions": []
    },
    {
      "action": "admin::marketplace.plugins.uninstall",
      "subject": null,
      "properties": {},
      "conditions": []
    },
    {
      "action": "admin::marketplace.read",
      "subject": null,
      "properties": {},
      "conditions": []
    },
    {
      "action": "admin::roles.create",
      "subject": null,
      "properties": {},
      "conditions": []
    },
    {
      "action": "admin::roles.delete",
      "subject": null,
      "properties": {},
      "conditions": []
    },
    {
      "action": "admin::roles.read",
      "subject": null,
      "properties": {},
      "conditions": []
    },
    {
      "action": "admin::roles.update",
      "subject": null,
      "properties": {},
      "conditions": []
    },
    {
      "action": "admin::users.create",
      "subject": null,
      "properties": {},
      "conditions": []
    },
    {
      "action": "admin::users.delete",
      "subject": null,
      "properties": {},
      "conditions": []
    },
    {
      "action": "admin::users.read",
      "subject": null,
      "properties": {},
      "conditions": []
    },
    {
      "action": "admin::users.update",
      "subject": null,
      "properties": {},
      "conditions": []
    },
    {
      "action": "admin::webhooks.create",
      "subject": null,
      "properties": {},
      "conditions": []
    },
    {
      "action": "admin::webhooks.delete",
      "subject": null,
      "properties": {},
      "conditions": []
    },
    {
      "action": "admin::webhooks.read",
      "subject": null,
      "properties": {},
      "conditions": []
    },
    {
      "action": "admin::webhooks.update",
      "subject": null,
      "properties": {},
      "conditions": []
    },
    {
      "action": "plugin::config-sync.menu-link",
      "subject": null,
      "properties": {},
      "conditions": []
    },
    {
      "action": "plugin::config-sync.settings.read",
      "subject": null,
      "properties": {},
      "conditions": []
    },
    {
      "action": "plugin::content-manager.collection-types.configure-view",
      "subject": null,
      "properties": {},
      "conditions": []
    },
    {
      "action": "plugin::content-manager.components.configure-layout",
      "subject": null,
      "properties": {},
      "conditions": []
    },
    {
      "action": "plugin::content-manager.explorer.create",
      "subject": "plugin::users-permissions.user",
      "properties": {
        "fields": [
          "username",
          "email",
          "provider",
          "password",
          "resetPasswordToken",
          "confirmationToken",
          "confirmed",
          "blocked",
          "role"
        ]
      },
      "conditions": []
    },
    {
      "action": "plugin::content-manager.explorer.delete",
      "subject": "plugin::users-permissions.user",
      "properties": {},
      "conditions": []
    },
    {
      "action": "plugin::content-manager.explorer.read",
      "subject": "plugin::users-permissions.user",
      "properties": {
        "fields": [
          "username",
          "email",
          "provider",
          "password",
          "resetPasswordToken",
          "confirmationToken",
          "confirmed",
          "blocked",
          "role"
        ]
      },
      "conditions": []
    },
    {
      "action": "plugin::content-manager.explorer.update",
      "subject": "plugin::users-permissions.user",
      "properties": {
        "fields": [
          "username",
          "email",
          "provider",
          "password",
          "resetPasswordToken",
          "confirmationToken",
          "confirmed",
          "blocked",
          "role"
        ]
      },
      "conditions": []
    },
    {
      "action": "plugin::content-manager.single-types.configure-view",
      "subject": null,
      "properties": {},
      "conditions": []
    },
    {
      "action": "plugin::content-type-builder.read",
      "subject": null,
      "properties": {},
      "conditions": []
    },
    {
      "action": "plugin::documentation.read",
      "subject": null,
      "properties": {},
      "conditions": []
    },
    {
      "action": "plugin::documentation.settings.read",
      "subject": null,
      "properties": {},
      "conditions": []
    },
    {
      "action": "plugin::documentation.settings.regenerate",
      "subject": null,
      "properties": {},
      "conditions": []
    },
    {
      "action": "plugin::documentation.settings.update",
      "subject": null,
      "properties": {},
      "conditions": []
    },
    {
      "action": "plugin::email.settings.read",
      "subject": null,
      "properties": {},
      "conditions": []
    },
    {
      "action": "plugin::i18n.locale.create",
      "subject": null,
      "properties": {},
      "conditions": []
    },
    {
      "action": "plugin::i18n.locale.delete",
      "subject": null,
      "properties": {},
      "conditions": []
    },
    {
      "action": "plugin::i18n.locale.read",
      "subject": null,
      "properties": {},
      "conditions": []
    },
    {
      "action": "plugin::i18n.locale.update",
      "subject": null,
      "properties": {},
      "conditions": []
    },
    {
      "action": "plugin::upload.assets.copy-link",
      "subject": null,
      "properties": {},
      "conditions": []
    },
    {
      "action": "plugin::upload.assets.create",
      "subject": null,
      "properties": {},
      "conditions": []
    },
    {
      "action": "plugin::upload.assets.download",
      "subject": null,
      "properties": {},
      "conditions": []
    },
    {
      "action": "plugin::upload.assets.update",
      "subject": null,
      "properties": {},
      "conditions": []
    },
    {
      "action": "plugin::upload.read",
      "subject": null,
      "properties": {},
      "conditions": []
    },
    {
      "action": "plugin::upload.settings.read",
      "subject": null,
      "properties": {},
      "conditions": []
    },
    {
      "action": "plugin::users-permissions.advanced-settings.read",
      "subject": null,
      "properties": {},
      "conditions": []
    },
    {
      "action": "plugin::users-permissions.advanced-settings.update",
      "subject": null,
      "properties": {},
      "conditions": []
    },
    {
      "action": "plugin::users-permissions.email-templates.read",
      "subject": null,
      "properties": {},
      "conditions": []
    },
    {
      "action": "plugin::users-permissions.email-templates.update",
      "subject": null,
      "properties": {},
      "conditions": []
    },
    {
      "action": "plugin::users-permissions.providers.read",
      "subject": null,
      "properties": {},
      "conditions": []
    },
    {
      "action": "plugin::users-permissions.providers.update",
      "subject": null,
      "properties": {},
      "conditions": []
    },
    {
      "action": "plugin::users-permissions.roles.create",
      "subject": null,
      "properties": {},
      "conditions": []
    },
    {
      "action": "plugin::users-permissions.roles.delete",
      "subject": null,
      "properties": {},
      "conditions": []
    },
    {
      "action": "plugin::users-permissions.roles.read",
      "subject": null,
      "properties": {},
      "conditions": []
    },
    {
      "action": "plugin::users-permissions.roles.update",
      "subject": null,
      "properties": {},
      "conditions": []
    }
  ]
}